Dev_Jyoti/Verilog_Q2/sequential_Q2.v
module sequential_Q2(input clk,a,rstn, output reg b,c);
  always@(posedge clk or negedge rstn) begin
    if(!rstn) begin
      b<=0;
      c<=0;
    end else begin
      b<=a;
      c<=b;
    end
  end
endmodule

Dev_Jyoti/Verilog_Q2/sequential_Q2_tb.v
`include "sequential_Q2.v"
`timescale 1ns/1ps
module sequential_Q2_tb;
  reg clk,rstn,a;
  wire b,c;
  sequential_Q2 test(
    .clk(clk), .rstn(rstn), .a(a), .b(b), .c(c)
  );
  always #5 clk= ~clk;
  initial begin
    clk=0;
    rstn=0;
    a=0;
    #10 rstn=1;
    #10 a=1;
    #10 a=0;
    #10 a=1;
    #10 a=0;
    #50;
    $finish;
  end
  initial begin
    $monitor("Time=%0t | clk=%b | rstn=%b | a=%b | b=%b | c=%b", $time,clk,rstn,a,b,c);
    $dumpfile("waveform.vcd");
    $dumpvars(1);
  end
endmodule

Dev_Jyoti/Verilog_Q2/waveform.vcd
$date
	Sun Mar 16 18:18:17 2025
$end
$version
	Icarus Verilog
$end
$timescale
	1ps
$end
$scope module sequential_Q2_tb $end
$var wire 1 ! c $end
$var wire 1 " b $end
$var reg 1 # a $end
$var reg 1 $ clk $end
$var reg 1 % rstn $end
$upscope $end
$enddefinitions $end
$comment Show the parameter values. $end
$dumpall
$end
#0
$dumpvars
0%
0$
0#
0"
0!
$end
#5000
1$
#10000
0$
1%
#15000
1$
#20000
0$
1#
#25000
1"
1$
#30000
0$
0#
#35000
1!
0"
1$
#40000
0$
1#
#45000
0!
1"
1$
#50000
0$
0#
#55000
1!
0"
1$
#60000
0$
#65000
0!
1$
