Dev_Jyoti/Verilog_Q3/pos_edgedetector_Q3.v
module pos_edgedetector_Q3(input clk, rstn, a, output reg b);
  reg a_prev;//stores the previous state of a
  always @(posedge clk or negedge rstn) begin
    if(!rstn) begin
      a_prev<=0;
      b<=0;
    end else begin
      b<=(~a_prev & a);
      a_prev<=a;
    end
  end
endmodule

Dev_Jyoti/Verilog_Q3/pos_edgedetector_Q3_tb.v
`include "pos_edgedetector_Q3.v"
`timescale 1ns/1ps
module pos_edgedetector_Q3_tb;
  reg clk,rstn,a;
  wire b;
  pos_edgedetector_Q3 test(
    .clk(clk), .rstn(rstn), .a(a), .b(b)
  );
  always #5 clk= ~clk;
  initial begin
    rstn=0;
    clk=0;
    a=0;
    #10 rstn=1;
    #10 a=1; //+ve edge
    #10 a=1;
    #10 a=0;
    #10 a=1; //+ve edge
    #10 a=0;
    #10 rstn=0;
    #10 rstn=1;
    #50 $finish;
  end
  initial begin
    $monitor("Time=%0t | rstn=%b | clk=%b | a=%b | b=%b", $time,rstn,clk,a,b);
    $dumpfile("waveform.vcd");
    $dumpvars(1);
  end
endmodule

Dev_Jyoti/Verilog_Q3/waveform.vcd
$date
	Sun Mar 16 20:36:32 2025
$end
$version
	Icarus Verilog
$end
$timescale
	1ps
$end
$scope module pos_edgedetector_Q3_tb $end
$var wire 1 ! b $end
$var reg 1 " a $end
$var reg 1 # clk $end
$var reg 1 $ rstn $end
$upscope $end
$enddefinitions $end
$comment Show the parameter values. $end
$dumpall
$end
#0
$dumpvars
0$
0#
0"
0!
$end
#5000
1#
#10000
0#
1$
#15000
1#
#20000
0#
1"
#25000
1!
1#
#30000
0#
#35000
0!
1#
#40000
0#
0"
#45000
1#
#50000
0#
1"
#55000
1!
1#
#60000
0#
0"
#65000
0!
1#
#70000
0#
0$
#75000
1#
#80000
0#
1$
